{
  "gitSyncId": "68e2763c7b259b69c39690c9_5af8874d-4f92-4308-916e-b5ee9cb9bfd5",
  "id": "Quizzes_getQuizForStatus",
  "pluginId": "restapi-plugin",
  "pluginType": "API",
  "unpublishedAction": {
    "actionConfiguration": {
      "autoGeneratedHeaders": [],
      "body": "",
      "bodyFormData": [],
      "encodeParamsToggle": true,
      "formData": {
        "apiContentType": "none"
      },
      "headers": [],
      "httpMethod": "GET",
      "httpVersion": "HTTP11",
      "paginationType": "NONE",
      "path": "/api/v1/quiz",
      "pluginSpecifiedTemplates": [
        {
          "value": true
        }
      ],
      "queryParameters": [],
      "timeoutInMillisecond": 10000
    },
    "confirmBeforeExecute": false,
    "datasource": {
      "id": "QuizboxBD Prod API",
      "isAutoGenerated": false,
      "name": "QuizboxBD Prod API",
      "pluginId": "restapi-plugin"
    },
    "dynamicBindingPathList": [
      {
        "key": "path"
      },
      {
        "key": "queryParameters[0].value"
      }
    ],
    "name": "getQuizForStatus",
    "pageId": "Quizzes",
    "runBehaviour": "MANUAL",
    "userSetOnLoad": false
  }
}