{
  "gitSyncId": "696bb90d1c0704487d1a737a_87a811cc-1ff3-4c1a-935e-e8342d00dbeb",
  "id": "Questions_ImportPoller.poll",
  "pluginId": "js-plugin",
  "pluginType": "JS",
  "unpublishedAction": {
    "actionConfiguration": {
      "encodeParamsToggle": true,
      "jsArguments": [],
      "paginationType": "NONE",
      "timeoutInMillisecond": 10000
    },
    "collectionId": "Questions_ImportPoller",
    "confirmBeforeExecute": false,
    "datasource": {
      "isAutoGenerated": false,
      "name": "UNUSED_DATASOURCE",
      "pluginId": "js-plugin"
    },
    "dynamicBindingPathList": [
      {
        "key": "body"
      }
    ],
    "fullyQualifiedName": "ImportPoller.poll",
    "name": "poll",
    "pageId": "Questions",
    "runBehaviour": "MANUAL",
    "userSetOnLoad": false
  }
}